fix_my_functions/__init__.py
fix_my_functions/__main__.py
fix_my_functions/config.py
fix_my_functions/formatters.py
fix_my_functions/helpers.py
fix_my_functions/runner.py
fix_my_functions-0.1.3.dist-info/entry_points.txt
fix_my_functions-0.1.3.dist-info/WHEEL
fix_my_functions-0.1.3.dist-info/METADATA
fix_my_functions-0.1.3.dist-info/RECORD
