Metadata-Version: 2.1
Name: fix-my-functions
Version: 0.1.3
Summary: 
Author: Peder Bergebakken Sundt
Author-email: pbsds@hotmail.com
Requires-Python: >=3.9
Classifier: Programming Language :: Python :: 3
Classifier: Programming Language :: Python :: 3.10
Classifier: Programming Language :: Python :: 3.9
Requires-Dist: colorama (>=0.4.4)
Requires-Dist: redbaron (>=0.9.2)
